src/__init__.py
src/enums.py
src/exception.py
src/logs.py
src/upload.py
src/utils.py
youtube_selenium_cookie-0.2.dist-info/METADATA
youtube_selenium_cookie-0.2.dist-info/WHEEL
youtube_selenium_cookie-0.2.dist-info/top_level.txt
youtube_selenium_cookie-0.2.dist-info/RECORD
